Workbook

Sheet Simulador SAC x PRICE
B1: PLANILHA DE FINANCIAMENTO
B2: Comparativo SAC x PRICE — projetei.com | Edição JUL/2026
B4: DADOS DE ENTRADA
B5: Valor Total da Construção (R$) | C5: 600000
B6: Entrada (%) | C6: 0.2
B7: Tempo do Financiamento (anos) | C7: 15
B8: Taxa de Juros ao mês (Caixa) | C8: 0,0075
B9: Valor da Entrada (R$) | C9: =(C5*C6) -> 120000
B10: Valor Financiado (R$) | C10: =C5-C9 -> 480000
B11: Total de Parcelas | C11: =C7*12 -> 180
B15: SIMULAÇÃO — SISTEMA SAC (Amortização Constante) | H15: SIMULAÇÃO — TABELA PRICE (Parcela Fixa)
C16: Amortização | D16: Juros | E16: Parcela Total | F16: Saldo Devedor | H16: Parcela Fixa | I16: Amort + Juros | J16: Saldo Devedor
B17: 1 | C17: =IF(B17>$C$11,"", $C$10/$C$11) -> 2666.6667 | D17: =IF(B17>$C$11,"", $C$10*$C$8) -> 3600 | E17: =IF(B17>$C$11,"", C17+D17) -> 6266.6667 | F17: =IF(B17>$C$11,"", $C$10-C17) -> 477333.33 | H17: =IF(B17>$C$11,"", $C$10*($C$8*(1+$C$8)^$C$11)/((1+$C$8)^$C$11-1)) -> 4868.4796 | I17: =IF(B17>$C$11,"", H17-($C$10*$C$8)) -> 1268.4796 | J17: =IF(B17>$C$11,"", $C$10-I17) -> 478731.52
B18: 2 | C18: =IF(B18>$C$11,"", $C$10/$C$11) -> 2666.6667 | D18: =IF(B18>$C$11,"", F17*$C$8) -> 3580 | E18: =IF(B18>$C$11,"", C18+D18) -> 6246.6667 | F18: =IF(B18>$C$11,"", F17-C18) -> 474666.67 | H18: =IF(B18>$C$11,"", $C$10*($C$8*(1+$C$8)^$C$11)/((1+$C$8)^$C$11-1)) -> 4868.4796 | I18: =IF(B18>$C$11,"", H18-(J17*$C$8)) -> 1277.9932 | J18: =IF(B18>$C$11,"", J17-I18) -> 477453.53
B19: 3 | C19: =IF(B19>$C$11,"", $C$10/$C$11) -> 2666.6667 | D19: =IF(B19>$C$11,"", F18*$C$8) -> 3560 | E19: =IF(B19>$C$11,"", C19+D19) -> 6226.6667 | F19: =IF(B19>$C$11,"", F18-C19) -> 472000 | H19: =IF(B19>$C$11,"", $C$10*($C$8*(1+$C$8)^$C$11)/((1+$C$8)^$C$11-1)) -> 4868.4796 | I19: =IF(B19>$C$11,"", H19-(J18*$C$8)) -> 1287.5782 | J19: =IF(B19>$C$11,"", J18-I19) -> 476165.95
B20: 4 | C20: =IF(B20>$C$11,"", $C$10/$C$11) -> 2666.6667 | D20: =IF(B20>$C$11,"", F19*$C$8) -> 3540 | E20: =IF(B20>$C$11,"", C20+D20) -> 6206.6667 | F20: =IF(B20>$C$11,"", F19-C20) -> 469333.33 | H20: =IF(B20>$C$11,"", $C$10*($C$8*(1+$C$8)^$C$11)/((1+$C$8)^$C$11-1)) -> 4868.4796 | I20: =IF(B20>$C$11,"", H20-(J19*$C$8)) -> 1297.235 | J20: =IF(B20>$C$11,"", J19-I20) -> 474868.71
B21: 5 | C21: =IF(B21>$C$11,"", $C$10/$C$11) -> 2666.6667 | D21: =IF(B21>$C$11,"", F20*$C$8) -> 3520 | E21: =IF(B21>$C$11,"", C21+D21) -> 6186.6667 | F21: =IF(B21>$C$11,"", F20-C21) -> 466666.67 | H21: =IF(B21>$C$11,"", $C$10*($C$8*(1+$C$8)^$C$11)/((1+$C$8)^$C$11-1)) -> 4868.4796 | I21: =IF(B21>$C$11,"", H21-(J20*$C$8)) -> 1306.9642 | J21: =IF(B21>$C$11,"", J20-I21) -> 473561.75
B22: 6 | C22: =IF(B22>$C$11,"", $C$10/$C$11) -> 2666.6667 | D22: =IF(B22>$C$11,"", F21*$C$8) -> 3500 | E22: =IF(B22>$C$11,"", C22+D22) -> 6166.6667 | F22: =IF(B22>$C$11,"", F21-C22) -> 464000 | H22: =IF(B22>$C$11,"", $C$10*($C$8*(1+$C$8)^$C$11)/((1+$C$8)^$C$11-1)) -> 4868.4796 | I22: =IF(B22>$C$11,"", H22-(J21*$C$8)) -> 1316.7665 | J22: =IF(B22>$C$11,"", J21-I22) -> 472244.98
B23: 7 | C23: =IF(B23>$C$11,"", $C$10/$C$11) -> 2666.6667 | D23: =IF(B23>$C$11,"", F22*$C$8) -> 3480 | E23: =IF(B23>$C$11,"", C23+D23) -> 6146.6667 | F23: =IF(B23>$C$11,"", F22-C23) -> 461333.33 | H23: =IF(B23>$C$11,"", $C$10*($C$8*(1+$C$8)^$C$11)/((1+$C$8)^$C$11-1)) -> 4868.4796 | I23: =IF(B23>$C$11,"", H23-(J22*$C$8)) -> 1326.6422 | J23: =IF(B23>$C$11,"", J22-I23) -> 470918.34
B24: 8 | C24: =IF(B24>$C$11,"", $C$10/$C$11) -> 2666.6667 | D24: =IF(B24>$C$11,"", F23*$C$8) -> 3460 | E24: =IF(B24>$C$11,"", C24+D24) -> 6126.6667 | F24: =IF(B24>$C$11,"", F23-C24) -> 458666.67 | H24: =IF(B24>$C$11,"", $C$10*($C$8*(1+$C$8)^$C$11)/((1+$C$8)^$C$11-1)) -> 4868.4796 | I24: =IF(B24>$C$11,"", H24-(J23*$C$8)) -> 1336.592 | J24: =IF(B24>$C$11,"", J23-I24) -> 469581.75
B25: 9 | C25: =IF(B25>$C$11,"", $C$10/$C$11) -> 2666.6667 | D25: =IF(B25>$C$11,"", F24*$C$8) -> 3440 | E25: =IF(B25>$C$11,"", C25+D25) -> 6106.6667 | F25: =IF(B25>$C$11,"", F24-C25) -> 456000 | H25: =IF(B25>$C$11,"", $C$10*($C$8*(1+$C$8)^$C$11)/((1+$C$8)^$C$11-1)) -> 4868.4796 | I25: =IF(B25>$C$11,"", H25-(J24*$C$8)) -> 1346.6165 | J25: =IF(B25>$C$11,"", J24-I25) -> 468235.13
B26: 10 | C26: =IF(B26>$C$11,"", $C$10/$C$11) -> 2666.6667 | D26: =IF(B26>$C$11,"", F25*$C$8) -> 3420 | E26: =IF(B26>$C$11,"", C26+D26) -> 6086.6667 | F26: =IF(B26>$C$11,"", F25-C26) -> 453333.33 | H26: =IF(B26>$C$11,"", $C$10*($C$8*(1+$C$8)^$C$11)/((1+$C$8)^$C$11-1)) -> 4868.4796 | I26: =IF(B26>$C$11,"", H26-(J25*$C$8)) -> 1356.7161 | J26: =IF(B26>$C$11,"", J25-I26) -> 466878.42
B27: 11 | C27: =IF(B27>$C$11,"", $C$10/$C$11) -> 2666.6667 | D27: =IF(B27>$C$11,"", F26*$C$8) -> 3400 | E27: =IF(B27>$C$11,"", C27+D27) -> 6066.6667 | F27: =IF(B27>$C$11,"", F26-C27) -> 450666.67 | H27: =IF(B27>$C$11,"", $C$10*($C$8*(1+$C$8)^$C$11)/((1+$C$8)^$C$11-1)) -> 4868.4796 | I27: =IF(B27>$C$11,"", H27-(J26*$C$8)) -> 1366.8915 | J27: =IF(B27>$C$11,"", J26-I27) -> 465511.52
B28: 12 | C28: =IF(B28>$C$11,"", $C$10/$C$11) -> 2666.6667 | D28: =IF(B28>$C$11,"", F27*$C$8) -> 3380 | E28: =IF(B28>$C$11,"", C28+D28) -> 6046.6667 | F28: =IF(B28>$C$11,"", F27-C28) -> 448000 | H28: =IF(B28>$C$11,"", $C$10*($C$8*(1+$C$8)^$C$11)/((1+$C$8)^$C$11-1)) -> 4868.4796 | I28: =IF(B28>$C$11,"", H28-(J27*$C$8)) -> 1377.1432 | J28: =IF(B28>$C$11,"", J27-I28) -> 464134.38
B29: 13 | C29: =IF(B29>$C$11,"", $C$10/$C$11) -> 2666.6667 | D29: =IF(B29>$C$11,"", F28*$C$8) -> 3360 | E29: =IF(B29>$C$11,"", C29+D29) -> 6026.6667 | F29: =IF(B29>$C$11,"", F28-C29) -> 445333.33 | H29: =IF(B29>$C$11,"", $C$10*($C$8*(1+$C$8)^$C$11)/((1+$C$8)^$C$11-1)) -> 4868.4796 | I29: =IF(B29>$C$11,"", H29-(J28*$C$8)) -> 1387.4717 | J29: =IF(B29>$C$11,"", J28-I29) -> 462746.91
... B376: 360 | C376: =IF(B376>$C$11,"", $C$10/$C$11) | D376: =IF(B376>$C$11,"", F375*$C$8) | E376: =IF(B376>$C$11,"", C376+D376) | F376: =IF(B376>$C$11,"", F375-C376) | H376: =IF(B376>$C$11,"", $C$10*($C$8*(1+$C$8)^$C$11)/((1+$C$8)^$C$11-1)) | I376: =IF(B376>$C$11,"", H376-(J375*$C$8)) | J376: =IF(B376>$C$11,"", J375-I376)
B377: TOTAL | C377: =SUM(C17:C376) -> 480000 | D377: =SUM(D17:D376) -> 325800 | E377: =SUM(E17:E376) -> 805800 | H377: TOTAL | I377: =SUM(I17:I376) -> 480000 | J377: =SUM(H17:H376) -> 876326.33

Sheet Resumo Comparativo
B1: RESUMO COMPARATIVO — SAC x PRICE
B2: projetei.com — Edição JUL/2026
B4: VALOR DA CONSTRUÇÃO | C4: ='Simulador SAC x PRICE'!C5 -> 600000
B5: ENTRADA | C5: ='Simulador SAC x PRICE'!C9 -> 120000
B6: VALOR FINANCIADO | C6: ='Simulador SAC x PRICE'!C10 -> 480000
B7: PRAZO | C7: 15 ANOS
B8: TAXA MENSAL | C8: ='Simulador SAC x PRICE'!C8 -> 0,0075
B10: COMPARATIVO ENTRE SISTEMAS
B11: Indicador | C11: SAC | D11: PRICE | E11: Diferença
B12: Parcela Inicial | C12: ='Simulador SAC x PRICE'!E17 -> 6266.6667 | D12: ='Simulador SAC x PRICE'!H17 -> 4868.4796 | E12: =C12-D12 -> 1398.1871
B13: Parcela Final | C13: ='Simulador SAC x PRICE'!E196 -> 2686.6667 | D13: ='Simulador SAC x PRICE'!H17 -> 4868.4796 | E13: =C13-D13 -> -2181.8129
B14: Total Pago ao Final | C14: ='Simulador SAC x PRICE'!E377 -> 805800 | D14: ='Simulador SAC x PRICE'!J377 -> 876326.33 | E14: =C14-D14 -> -70526.329
B15: Total de Juros Pagos | C15: ='Simulador SAC x PRICE'!D377 -> 325800 | D15: =('Simulador SAC x PRICE'!J377)-('Simulador SAC x PRICE'!C10) -> 396326.33 | E15: =C15-D15 -> -70526.329
B17: VEREDICTO
B18: =IF(C15<D15, "O SAC é mais econômico neste caso! Economia de "&TEXT(ABS(D15-C15),"R$ #.##0,00"), IF(D15<C15, "O PRICE é mais econômico neste caso! Economia de "&TEXT(ABS(C15-D15),"R$ #.##0,00"), "Ambos resultam no mesmo custo total.")) -> O SAC é mais econômico neste caso! Economia de R$ 70.526,33
B20: ANÁLISE RÁPIDA
B21: ▸ O SAC tem parcelas iniciais MAIORES, mas diminuem ao longo do tempo — ideal quem tem renda que vai crescer.
B22: ▸ O PRICE tem parcelas FIXAS durante todo o financiamento — ideal para quem quer previsibilidade.
B23: ▸ Em financiamentos curtos (Até 10 anos), o PRICE pode ser competitivo.
B24: ▸ Em financiamentos longos (15-30 anos), o SAC quase sempre é mais barato no total.
B25: ▸ A diferença total entre eles pode chegar a dezenas de milhares de reais.

Sheet Gráficos
B1: GRÁFICOS — PRIMEIROS 60 MESES
B3: Mês | C3: Parcela SAC | D3: Parcela PRICE | E3: Saldo SAC | F3: Saldo PRICE
B4: 1 | C4: ='Simulador SAC x PRICE'!E17 -> 6266.6667 | D4: ='Simulador SAC x PRICE'!H17 -> 4868.4796 | E4: ='Simulador SAC x PRICE'!F17 -> 477333.33 | F4: ='Simulador SAC x PRICE'!J17 -> 478731.52
B5: 2 | C5: ='Simulador SAC x PRICE'!E18 -> 6246.6667 | D5: ='Simulador SAC x PRICE'!H18 -> 4868.4796 | E5: ='Simulador SAC x PRICE'!F18 -> 474666.67 | F5: ='Simulador SAC x PRICE'!J18 -> 477453.53
B6: 3 | C6: ='Simulador SAC x PRICE'!E19 -> 6226.6667 | D6: ='Simulador SAC x PRICE'!H19 -> 4868.4796 | E6: ='Simulador SAC x PRICE'!F19 -> 472000 | F6: ='Simulador SAC x PRICE'!J19 -> 476165.95
B7: 4 | C7: ='Simulador SAC x PRICE'!E20 -> 6206.6667 | D7: ='Simulador SAC x PRICE'!H20 -> 4868.4796 | E7: ='Simulador SAC x PRICE'!F20 -> 469333.33 | F7: ='Simulador SAC x PRICE'!J20 -> 474868.71
B8: 5 | C8: ='Simulador SAC x PRICE'!E21 -> 6186.6667 | D8: ='Simulador SAC x PRICE'!H21 -> 4868.4796 | E8: ='Simulador SAC x PRICE'!F21 -> 466666.67 | F8: ='Simulador SAC x PRICE'!J21 -> 473561.75
B9: 6 | C9: ='Simulador SAC x PRICE'!E22 -> 6166.6667 | D9: ='Simulador SAC x PRICE'!H22 -> 4868.4796 | E9: ='Simulador SAC x PRICE'!F22 -> 464000 | F9: ='Simulador SAC x PRICE'!J22 -> 472244.98
B10: 7 | C10: ='Simulador SAC x PRICE'!E23 -> 6146.6667 | D10: ='Simulador SAC x PRICE'!H23 -> 4868.4796 | E10: ='Simulador SAC x PRICE'!F23 -> 461333.33 | F10: ='Simulador SAC x PRICE'!J23 -> 470918.34
B11: 8 | C11: ='Simulador SAC x PRICE'!E24 -> 6126.6667 | D11: ='Simulador SAC x PRICE'!H24 -> 4868.4796 | E11: ='Simulador SAC x PRICE'!F24 -> 458666.67 | F11: ='Simulador SAC x PRICE'!J24 -> 469581.75
B12: 9 | C12: ='Simulador SAC x PRICE'!E25 -> 6106.6667 | D12: ='Simulador SAC x PRICE'!H25 -> 4868.4796 | E12: ='Simulador SAC x PRICE'!F25 -> 456000 | F12: ='Simulador SAC x PRICE'!J25 -> 468235.13
B13: 10 | C13: ='Simulador SAC x PRICE'!E26 -> 6086.6667 | D13: ='Simulador SAC x PRICE'!H26 -> 4868.4796 | E13: ='Simulador SAC x PRICE'!F26 -> 453333.33 | F13: ='Simulador SAC x PRICE'!J26 -> 466878.42
B14: 11 | C14: ='Simulador SAC x PRICE'!E27 -> 6066.6667 | D14: ='Simulador SAC x PRICE'!H27 -> 4868.4796 | E14: ='Simulador SAC x PRICE'!F27 -> 450666.67 | F14: ='Simulador SAC x PRICE'!J27 -> 465511.52
B15: 12 | C15: ='Simulador SAC x PRICE'!E28 -> 6046.6667 | D15: ='Simulador SAC x PRICE'!H28 -> 4868.4796 | E15: ='Simulador SAC x PRICE'!F28 -> 448000 | F15: ='Simulador SAC x PRICE'!J28 -> 464134.38
... B63: 60 | C63: ='Simulador SAC x PRICE'!E76 -> 5086.6667 | D63: ='Simulador SAC x PRICE'!H76 -> 4868.4796 | E63: ='Simulador SAC x PRICE'!F76 -> 320000 | F63: ='Simulador SAC x PRICE'!J76 -> 384326.02
